pykongregate/api.py
pykongregate/__init__.py
pykongregate/models.py
pykongregate/exceptions.py
pykongregate-0.0.2.4.dist-info/DESCRIPTION.rst
pykongregate-0.0.2.4.dist-info/top_level.txt
pykongregate-0.0.2.4.dist-info/WHEEL
pykongregate-0.0.2.4.dist-info/RECORD
pykongregate-0.0.2.4.dist-info/metadata.json
pykongregate-0.0.2.4.dist-info/METADATA
