Metadata-Version: 2.0
Name: pykongregate
Version: 0.0.2.4
Summary: python client for kongregate REST API
Home-page: UNKNOWN
Author: Korvyashka <korvyashka666@gmail.com>
Author-email: korvyashka666@gmail.com
License: MIT license
Download-URL: https://github.com/korvyashka/pykongregate.git
Platform: OS Independent
Classifier: Development Status :: 1 - Planning
Classifier: Environment :: Console
Classifier: Intended Audience :: Developers
Classifier: License :: OSI Approved :: MIT License
Classifier: Operating System :: OS Independent
Classifier: Programming Language :: Python
Classifier: Natural Language :: English
Requires-Dist: simplejson
Requires-Dist: requests
